Metadata-Version: 2.1
Name: selenium-wire-2-uc
Version: 0.2.8
Summary: Extends Selenium to give you the ability to inspect requests made by the browser.
Home-page: https://github.com/unpacify/selenium-wire-2-uc
Author: unpacify
Author-email: copeyeu17@gmail.com
License: MIT
Keywords: selenium-wire-2
Classifier: Development Status :: 4 - Beta
Classifier: Intended Audience :: Developers
Classifier: License :: OSI Approved :: MIT License
Classifier: Natural Language :: English
Classifier: Operating System :: MacOS
Classifier: Operating System :: POSIX
Classifier: Operating System :: Microsoft :: Windows
Classifier: Programming Language :: Python :: 3.10
Classifier: Programming Language :: Python :: 3.11
Classifier: Programming Language :: Python :: 3.12
Requires-Python: >=3.10
License-File: LICENSE
License-File: NOTICES
License-File: AUTHORS.rst
Requires-Dist: mitmproxy>=10.3.0
Requires-Dist: selenium>=4.0.0
Requires-Dist: undetected-chromedriver>=3.0.0
Provides-Extra: test
Requires-Dist: httpbin; extra == "test"
Requires-Dist: pytest; extra == "test"
Requires-Dist: pytest-cov; extra == "test"
